pytest_pudb.py
fork_pytest_pudb-0.8.0.dist-info/licenses/LICENSE
fork_pytest_pudb-0.8.0.dist-info/METADATA
fork_pytest_pudb-0.8.0.dist-info/WHEEL
fork_pytest_pudb-0.8.0.dist-info/entry_points.txt
fork_pytest_pudb-0.8.0.dist-info/top_level.txt
fork_pytest_pudb-0.8.0.dist-info/RECORD
