Metadata-Version: 2.4
Name: fork-pytest-pudb
Version: 0.8.0
Summary: Pytest PuDB debugger integration fork for pytest >= 7
Home-page: https://github.com/wronglink/pytest-pudb
Author: Michael Elovskikh
Author-email: wronglink@gmail.com
License: MIT
Classifier: Development Status :: 3 - Alpha
Classifier: Topic :: Software Development :: Testing
Classifier: Intended Audience :: Developers
Classifier: Operating System :: OS Independent
License-File: LICENSE
Requires-Dist: pytest>=7.0
Requires-Dist: pudb
Provides-Extra: dev
Requires-Dist: pexpect; extra == "dev"
Requires-Dist: tox; extra == "dev"
Requires-Dist: flake8; extra == "dev"
Dynamic: author
Dynamic: author-email
Dynamic: classifier
Dynamic: home-page
Dynamic: license
Dynamic: license-file
Dynamic: provides-extra
Dynamic: requires-dist
Dynamic: summary
